py2g_libs/__init__.py
py2g_libs/arguments.py
py2g_libs/iter.py
py2g_libs/mean.py
py2g_libs/parallel.py
py2g_libs/progress.py
py2g_libs/time.py
py2g_utils/__init__.py
py2g_utils/arguments.py
py2g_utils/mean.py
py2g_utils/parallel.py
py2g_utils/progress.py
py2g_utils/time.py
py2g_libs-1.0.3.dist-info/METADATA
py2g_libs-1.0.3.dist-info/WHEEL
py2g_libs-1.0.3.dist-info/top_level.txt
py2g_libs-1.0.3.dist-info/RECORD
