Metadata-Version: 2.1
Name: py2g-libs
Version: 1.0.3
Summary: Some python libs
Home-page: https://github.com/habecker/py2g-libs
Author: Yannick Habecker
Author-email: dev@y2g.de
Requires-Dist: pyyaml
